{
    "people": [
        {
            "name": "Scott",
            "website": "stackabuse.com",
            "from": "Nebraska"
        },
        {
            "name": "Larry",
            "website": "google.com",
            "from": "Michigan"
        },
        {
            "name": "Tim",
            "website": "apple.com",
            "from": "Alabama"
        }
    ],
    "brain": {
        "weights": [
            [
                0.016288252657277735,
                0.03599656319125333,
                0.322360273526098,
                0.38416731848158436
            ],
            [
                0.9128780754224007,
                0.989053533575346,
                0.8828109046479048,
                0.8962717549577662
            ],
            [
                0.3941549820876691,
                0.15316989354515986,
                0.880790848517173,
                0.08130744428846726
            ]
        ],
        "bias": [
            -1,
            2,
            4,
            -7,
            1,
            10
        ],
        "nodes": 5
    }
}